<annotation>
  <folder>input_fog</folder>
  <filename>foggy-007.jpg</filename>
  <path>/home/kenmo/v_ws/OpenLabeling/main/input_fog/foggy-007.jpg</path>
  <source>
    <database>Unknown</database>
  </source>
  <size>
    <width>1280</width>
    <height>844</height>
    <depth>3</depth>
  </size>
  <segmented>0</segmented>
  <object>
    <name>car</name>
    <pose>Unspecified</pose>
    <truncated>0</truncated>
    <difficult>0</difficult>
    <bndbox>
      <xmin>414</xmin>
      <ymin>489</ymin>
      <xmax>558</xmax>
      <ymax>590</ymax>
    </bndbox>
  </object>
  <object>
    <name>car</name>
    <pose>Unspecified</pose>
    <truncated>0</truncated>
    <difficult>0</difficult>
    <bndbox>
      <xmin>288</xmin>
      <ymin>491</ymin>
      <xmax>431</xmax>
      <ymax>620</ymax>
    </bndbox>
  </object>
  <object>
    <name>car</name>
    <pose>Unspecified</pose>
    <truncated>0</truncated>
    <difficult>0</difficult>
    <bndbox>
      <xmin>884</xmin>
      <ymin>478</ymin>
      <xmax>1055</xmax>
      <ymax>614</ymax>
    </bndbox>
  </object>
  <object>
    <name>car</name>
    <pose>Unspecified</pose>
    <truncated>0</truncated>
    <difficult>0</difficult>
    <bndbox>
      <xmin>73</xmin>
      <ymin>463</ymin>
      <xmax>319</xmax>
      <ymax>656</ymax>
    </bndbox>
  </object>
  <object>
    <name>car</name>
    <pose>Unspecified</pose>
    <truncated>0</truncated>
    <difficult>0</difficult>
    <bndbox>
      <xmin>560</xmin>
      <ymin>489</ymin>
      <xmax>659</xmax>
      <ymax>560</ymax>
    </bndbox>
  </object>
  <object>
    <name>car</name>
    <pose>Unspecified</pose>
    <truncated>0</truncated>
    <difficult>0</difficult>
    <bndbox>
      <xmin>665</xmin>
      <ymin>449</ymin>
      <xmax>823</xmax>
      <ymax>589</ymax>
    </bndbox>
  </object>
  <object>
    <name>car</name>
    <pose>Unspecified</pose>
    <truncated>0</truncated>
    <difficult>0</difficult>
    <bndbox>
      <xmin>811</xmin>
      <ymin>472</ymin>
      <xmax>901</xmax>
      <ymax>544</ymax>
    </bndbox>
  </object>
  <object>
    <name>car</name>
    <pose>Unspecified</pose>
    <truncated>0</truncated>
    <difficult>0</difficult>
    <bndbox>
      <xmin>1092</xmin>
      <ymin>475</ymin>
      <xmax>1120</xmax>
      <ymax>527</ymax>
    </bndbox>
  </object>
  <object>
    <name>car</name>
    <pose>Unspecified</pose>
    <truncated>0</truncated>
    <difficult>0</difficult>
    <bndbox>
      <xmin>1116</xmin>
      <ymin>470</ymin>
      <xmax>1177</xmax>
      <ymax>527</ymax>
    </bndbox>
  </object>
  <object>
    <name>bus</name>
    <pose>Unspecified</pose>
    <truncated>0</truncated>
    <difficult>0</difficult>
    <bndbox>
      <xmin>901</xmin>
      <ymin>380</ymin>
      <xmax>1097</xmax>
      <ymax>568</ymax>
    </bndbox>
  </object>
  <object>
    <name>bus</name>
    <pose>Unspecified</pose>
    <truncated>0</truncated>
    <difficult>0</difficult>
    <bndbox>
      <xmin>803</xmin>
      <ymin>436</ymin>
      <xmax>899</xmax>
      <ymax>498</ymax>
    </bndbox>
  </object>
</annotation>
