<annotation>
  <folder>input_fog</folder>
  <filename>mist-048.jpg</filename>
  <path>/home/kenmo/v_ws/OpenLabeling/main/input_fog/mist-048.jpg</path>
  <source>
    <database>Unknown</database>
  </source>
  <size>
    <width>450</width>
    <height>450</height>
    <depth>3</depth>
  </size>
  <segmented>0</segmented>
  <object>
    <name>car</name>
    <pose>Unspecified</pose>
    <truncated>0</truncated>
    <difficult>0</difficult>
    <bndbox>
      <xmin>63</xmin>
      <ymin>242</ymin>
      <xmax>260</xmax>
      <ymax>388</ymax>
    </bndbox>
  </object>
  <object>
    <name>car</name>
    <pose>Unspecified</pose>
    <truncated>0</truncated>
    <difficult>0</difficult>
    <bndbox>
      <xmin>273</xmin>
      <ymin>205</ymin>
      <xmax>407</xmax>
      <ymax>323</ymax>
    </bndbox>
  </object>
</annotation>
